CHANGELOG.md
LICENSE
README.md
examples/README.md
qwstpad/__init__.py
qwstpad-0.0.1.dist-info/METADATA
qwstpad-0.0.1.dist-info/WHEEL
qwstpad-0.0.1.dist-info/licenses/LICENSE
qwstpad-0.0.1.dist-info/RECORD
